pyaudible/__init__.py
pyaudible/pyaudible.py
pyaudible/receiver.py
pyaudible/transmitter.py
pyaudible-1.1.0b3.dist-info/LICENSE
pyaudible-1.1.0b3.dist-info/METADATA
pyaudible-1.1.0b3.dist-info/WHEEL
pyaudible-1.1.0b3.dist-info/top_level.txt
pyaudible-1.1.0b3.dist-info/RECORD
