Metadata-Version: 2.1
Name: pyaudible
Version: 1.1.0b3
Summary: A Python library for sending and receiving data using audible sound.
Home-page: https://github.com/jasper-zheng/PyAudible
Author: Jasper Zheng (Shuoyang)
Author-email: s.zheng14@student.liverpool.ac.uk
License: UNKNOWN
Project-URL: Bug Tracker, https://github.com/jasper-zheng/PyAudible/issues
Platform: UNKNOWN
Classifier: Programming Language :: Python :: 3.8
Requires-Python: >=3.6
Requires-Dist: numpy
Requires-Dist: scipy
Requires-Dist: pyaudio
